[
  {
    "id": "arcana_sanguine_marks",
    "type": "magic_type",
    "energy_source": "STAMINA",
    "cannot_cast_flags": [ "NO_ARCANA_MAGIC", "NO_ARCANA_SANGUINE_MARKS", "NO_SPELLCASTING" ],
    "failure_cost_percent": 1,
    "max_book_level": 0,
    "cannot_cast_message": "You sanguine marks have no power!",
    "failure_chance_formula_id": "arcana_sanguine_mark_failure_chance"
  },
  {
    "id": "arcana_mark_revenant_blood",
    "type": "SPELL",
    "name": { "str": "Revenant Blood" },
    "description": "Using this spell will guard against poison, protect against pestilence in food and water, and burn out fungal influences or other parasites.",
    "message": "With a sign, you feel your blood burning with magical power.  %s!",
    "valid_targets": [ "self" ],
    "flags": [ "SOMATIC", "NO_HANDS" ],
    "effect": "attack",
    "shape": "blast",
    "effect_str": "dragonblood_clarity",
    "difficulty": 40,
    "skill": "magic",
    "max_level": 10,
    "base_casting_time": 150,
    "final_casting_time": 75,
    "casting_time_increment": -7.5,
    "base_energy_cost": 3200,
    "final_energy_cost": 1600,
    "energy_increment": -160,
    "min_duration": 48000,
    "max_duration": 120000,
    "duration_increment": 7200,
    "spell_class": "ARCANA_SANGUINE_MARKS",
    "magic_type": "arcana_sanguine_marks"
  },
  {
    "id": "arcana_mark_destructive_absorption",
    "type": "SPELL",
    "name": { "str": "Rending of the Veils" },
    "description": "Using this spell will drain energy from your surroundings, creating a void in reality that will heavily damage a single target, rapidly restoring your stamina afterward.  Beware the risk of tearing the fabric of reality.",
    "message": "With a strange gesture, the fabric of the Veil warps and decays.  %s!",
    "effect": "attack",
    "shape": "blast",
    "valid_targets": [ "ally", "hostile" ],
    "flags": [ "SILENT", "SOMATIC", "NO_HANDS", "RANDOM_DAMAGE" ],
    "extra_effects": [ { "id": "arcana_aftermath_destructive_absorption_side_effects", "hit_self": true, "max_level": 5 } ],
    "min_damage": { "math": [ "( u_spell_level('arcana_mark_destructive_absorption') * 8 ) + 60" ] },
    "max_damage": { "math": [ "( u_spell_level('arcana_mark_destructive_absorption') * 15 ) + 130" ] },
    "min_range": 3,
    "max_range": 6,
    "range_increment": 0.3,
    "skill": "magic",
    "max_level": 10,
    "difficulty": 100,
    "base_casting_time": 330,
    "final_casting_time": 165,
    "casting_time_increment": -16,
    "base_energy_cost": 8000,
    "final_energy_cost": 4000,
    "energy_increment": -400,
    "damage_type": "pure",
    "field_id": "fd_fatigue",
    "field_chance": 10,
    "min_field_intensity": 1,
    "max_field_intensity": 1,
    "spell_class": "ARCANA_SANGUINE_MARKS",
    "magic_type": "arcana_sanguine_marks"
  },
  {
    "id": "arcana_mark_surge_adrenaline",
    "//": "This spell is going away as a Mark but we'll put it here for now until I redo Sanguine Marks",
    "type": "SPELL",
    "name": { "str": "Surge of Fury" },
    "description": "Using this spell will provoke a rush of adrenaline for urgent situations, with none of the normal drawbacks.  That is not to say it has no drawbacks, as your mind will be filled with thoughts of violence.  It can only be used on yourself.",
    "message": "Your gestures provokes a rush of instinct, urging you to kill.  %s!",
    "valid_targets": [ "self" ],
    "flags": [ "SOMATIC", "NO_HANDS" ],
    "effect_str": "adrenaline_arcana_blood_magic",
    "max_level": 5,
    "effect": "attack",
    "shape": "blast",
    "base_casting_time": 90,
    "final_casting_time": 45,
    "casting_time_increment": -9,
    "base_energy_cost": 12,
    "final_energy_cost": 6,
    "energy_increment": -1.2,
    "difficulty": 20,
    "skill": "magic",
    "min_duration": 36000,
    "max_duration": 180000,
    "duration_increment": 28800,
    "spell_class": "ARCANA_SANGUINE_MARKS",
    "magic_type": "arcana_sanguine_marks"
  },
  {
    "id": "arcana_mark_displacing_slash",
    "type": "SPELL",
    "name": { "str": "Displacing Slash" },
    "description": "Using this spell will swap your position with a hostile target of your choosing.  While it won't directly damage your chosen target, anything caught in the bloody swath around where you emerge will be severely injured.",
    "message": "You lunge forward, arm outstretched toward your target.  %s!",
    "valid_targets": [ "hostile" ],
    "flags": [ "SILENT", "SOMATIC", "NO_HANDS", "SWAP_POS" ],
    "extra_effects": [ { "id": "arcana_aftermath_displacing_slash_aoe", "hit_self": false, "max_level": 5 } ],
    "effect": "attack",
    "shape": "blast",
    "effect_str": "downed",
    "difficulty": 40,
    "skill": "magic",
    "max_level": 10,
    "min_range": 10,
    "max_range": 30,
    "range_increment": 2,
    "base_casting_time": 150,
    "final_casting_time": 75,
    "casting_time_increment": -7,
    "base_energy_cost": 3000,
    "final_energy_cost": 1500,
    "energy_increment": -150,
    "min_duration": 2400,
    "max_duration": 6000,
    "duration_increment": 360,
    "field_id": "fd_blood",
    "field_chance": 1,
    "min_field_intensity": 1,
    "max_field_intensity": 3,
    "field_intensity_increment": 0.2,
    "field_intensity_variance": 0.5,
    "spell_class": "ARCANA_SANGUINE_MARKS",
    "magic_type": "arcana_sanguine_marks"
  },
  {
    "id": "arcana_mark_infernal_flame",
    "type": "SPELL",
    "name": { "str": "Infernal Breath" },
    "description": "Using this spell will channel your inner fire into a devastating blast, inflicting horrific burns and leaving a permanent scar upon the land.  Be careful using it around allies, and beware the risk of damaging the fabric of reality.",
    "message": "A bolt of flame leaps from your mouth, shaped into unholy fire with a wave of the hand.  %s!",
    "effect": "attack",
    "shape": "line",
    "valid_targets": [ "ally", "hostile", "ground" ],
    "flags": [ "SILENT", "SOMATIC", "NO_HANDS", "RANDOM_DAMAGE" ],
    "extra_effects": [
      { "id": "arcana_aftermath_brief_fire_ward", "hit_self": true },
      { "id": "arcana_aftermath_infernal_flame_corruption", "hit_self": false, "max_level": 5 },
      { "id": "arcana_aftermath_infernal_flame_field", "hit_self": false, "max_level": 5 },
      { "id": "arcana_aftermath_infernal_flame_noise", "hit_self": false, "max_level": 5 }
    ],
    "//": "Full damage with no spike effect, for single-target and line spells.",
    "min_damage": { "math": [ "( u_spell_level('arcana_mark_infernal_flame') * 7 ) + 50" ] },
    "max_damage": { "math": [ "( u_spell_level('arcana_mark_infernal_flame') * 12.5 ) + 120" ] },
    "effect_str": "bleed",
    "min_duration": 1400,
    "max_duration": 3500,
    "duration_increment": 420,
    "min_range": 10,
    "max_range": 15,
    "range_increment": 0.5,
    "max_level": 10,
    "difficulty": 70,
    "skill": "magic",
    "base_casting_time": 240,
    "final_casting_time": 120,
    "casting_time_increment": -12,
    "base_energy_cost": 4800,
    "final_energy_cost": 2400,
    "energy_increment": -240,
    "damage_type": "heat",
    "field_id": "fd_fire",
    "field_chance": 3,
    "min_field_intensity": 1,
    "max_field_intensity": 3,
    "field_intensity_increment": 0.4,
    "field_intensity_variance": 0.5,
    "spell_class": "ARCANA_SANGUINE_MARKS",
    "magic_type": "arcana_sanguine_marks"
  },
  {
    "id": "arcana_mark_drain_life",
    "type": "SPELL",
    "name": { "str": "Aura of Stolen Vitality" },
    "description": "Using this spell will anoint you with a horned halo, granting a life-draining effect.",
    "valid_targets": [ "self" ],
    "message": "You gesture, and are filled with a yearning for the hunt.  %s!",
    "flags": [ "SOMATIC", "NO_HANDS" ],
    "effect": "attack",
    "shape": "blast",
    "effect_str": "effect_arcana_blessing_drain_life_blood_magic",
    "difficulty": 60,
    "skill": "magic",
    "max_level": 10,
    "base_casting_time": 210,
    "final_casting_time": 105,
    "casting_time_increment": -10.5,
    "base_energy_cost": 4600,
    "final_energy_cost": 2300,
    "energy_increment": -230,
    "min_duration": 216000,
    "max_duration": 540000,
    "duration_increment": 32400,
    "spell_class": "ARCANA_SANGUINE_MARKS",
    "magic_type": "arcana_sanguine_marks"
  },
  {
    "id": "arcana_mark_call_bloodwalkers",
    "type": "SPELL",
    "name": { "str": "Summon the Blood-legions" },
    "description": "Using this spell will summon a group of bloodwalkers who will tear into your enemies.  With your superior command of blood magic, no external source of blood is required.",
    "message": "You make a thin cut on your palm and gesture toward your enemies.  %s!",
    "valid_targets": [ "ground", "ally", "hostile" ],
    "flags": [ "SOMATIC", "NO_HANDS" ],
    "effect": "summon",
    "shape": "blast",
    "effect_str": "mon_sanguine_blood_golem_summoned",
    "difficulty": 60,
    "skill": "magic",
    "max_level": 10,
    "min_damage": 2,
    "max_damage": 5,
    "damage_increment": 0.3,
    "min_range": 3,
    "max_range": 9,
    "range_increment": 0.6,
    "min_aoe": 2,
    "max_aoe": 2,
    "base_casting_time": 210,
    "final_casting_time": 105,
    "casting_time_increment": -10.5,
    "base_energy_cost": 4600,
    "final_energy_cost": 2300,
    "energy_increment": -230,
    "min_duration": 120000,
    "max_duration": 300000,
    "duration_increment": 18000,
    "spell_class": "ARCANA_SANGUINE_MARKS",
    "magic_type": "arcana_sanguine_marks"
  },
  {
    "id": "arcana_mark_elemental_sign",
    "type": "SPELL",
    "name": { "str": "Sign of the Inferno" },
    "description": "Using this spell will grant complete immunity to fire, spreading a deathly chill and driving away flames from your immediate area.",
    "message": "With a gesture, your inner fire flares up.  %s!",
    "valid_targets": [ "self" ],
    "flags": [ "SOMATIC", "NO_HANDS" ],
    "extra_effects": [
      { "id": "arcana_aftermath_brief_cold_ward", "hit_self": true },
      { "id": "arcana_aftermath_elemental_coldness", "hit_self": false, "max_level": 5 },
      { "id": "arcana_aftermath_elemental_field_effect", "hit_self": false, "max_level": 5 }
    ],
    "effect": "attack",
    "shape": "blast",
    "effect_str": "heat_ward_true_blood_magic",
    "difficulty": 50,
    "skill": "magic",
    "max_level": 5,
    "base_casting_time": 180,
    "final_casting_time": 90,
    "casting_time_increment": -18,
    "base_energy_cost": 24,
    "final_energy_cost": 12,
    "energy_increment": -2.4,
    "min_duration": 30000,
    "max_duration": 150000,
    "duration_increment": 24000,
    "spell_class": "ARCANA_SANGUINE_MARKS",
    "magic_type": "arcana_sanguine_marks"
  },
  {
    "id": "arcana_mark_malevolent_gaze",
    "type": "SPELL",
    "name": { "str": "Malevolent Gaze" },
    "description": "Using this spell will strike a single target with a powerful temporal effect.  It won't deal any damage, but it will freeze your prey in place momentarily, leaving them slowed for a while afterward.",
    "message": "Your pupils briefly narrow into thin slits as you focus your hatred.  %s!",
    "effect": "attack",
    "shape": "blast",
    "effect_str": "effect_arcana_malevolent_gaze",
    "valid_targets": [ "ally", "hostile" ],
    "flags": [ "SILENT", "SOMATIC", "NO_HANDS" ],
    "extra_effects": [ { "id": "arcana_aftermath_malevolent_gaze_slowdown", "hit_self": false, "max_level": 5 } ],
    "min_duration": 1000,
    "max_duration": 2500,
    "duration_increment": 300,
    "min_range": 5,
    "max_range": 10,
    "range_increment": 1,
    "max_level": 5,
    "difficulty": 50,
    "skill": "magic",
    "base_casting_time": 180,
    "final_casting_time": 90,
    "casting_time_increment": -18,
    "base_energy_cost": 24,
    "final_energy_cost": 12,
    "energy_increment": -2.4,
    "spell_class": "ARCANA_SANGUINE_MARKS",
    "magic_type": "arcana_sanguine_marks",
    "ignored_monster_species": [ "ROBOT", "ROBOT_FLYING" ]
  },
  {
    "id": "arcana_mark_might",
    "//": "ID retained for save compatibility reasons.",
    "type": "SPELL",
    "name": { "str": "Manifestation of Draconic Strength" },
    "description": "Using this spell will imbue your body with an unnatural aura, greatly increasing your strength and damage resistance, though with a correspondingly increased appetite.  It can only be used on yourself.",
    "valid_targets": [ "self" ],
    "flags": [ "SOMATIC", "NO_HANDS" ],
    "effect": "attack",
    "shape": "blast",
    "effect_str": "effect_arcana_manifestation_of_strength",
    "difficulty": 50,
    "skill": "magic",
    "max_level": 5,
    "min_damage": 1,
    "max_damage": 1,
    "base_casting_time": 180,
    "final_casting_time": 90,
    "casting_time_increment": -18,
    "base_energy_cost": 24,
    "final_energy_cost": 12,
    "energy_increment": -2.4,
    "min_duration": 60000,
    "max_duration": 150000,
    "duration_increment": 18000,
    "spell_class": "ARCANA_SANGUINE_MARKS",
    "magic_type": "arcana_sanguine_marks"
  }
]
